{
  "title": "AccruedInterest",
  "$schema": "http://json-schema.org/draft-07/schema#",
  "description": "Accrued interest",
  "type": "object",
  "required": [
    "businessChangeDate",
    "status",
    "instrumentIds",
    "validityDate",
    "aiValue",
    "currency",
    "nominalValue"
  ],
  "properties": {
    "X-Correlation-ID": {
      "type": [
        "string",
        "null"
      ],
      "title": "X-Correlation-ID",
      "description": "Korelační identifikátor, povinné pro INIT a RECON"
    },
    "businessChangeDate": {
      "description": "Datum a čas poslední změny entity",
      "type": "string",
      "format": "date-time"
    },
    "status": {
      "description": "Reflektuje stav fyzické existence záznamu: active - aktivní, deleted - samzáno",
      "type": "string",
      "enum": [
        "active",
        "deleted"
      ]
    },
    "instrumentIds": {
      "type": "object",
      "description": "Identifikátory CP",
      "$ref": "#/definitions/instrumentIds"
    },
    "validityDate": {
      "description": "Datum platnosti AÚV",
      "type": "string",
      "format": "date"
    },
    "aiValue": {
      "description": "Hodnota AÚV",
      "type": "number"
    },
    "currency": {
      "description": "Měna AÚV. ISO 4217 abecední kód (3 znaky). Číselník Currencies.",
      "type": "string"
    },
    "nominalValue": {
      "description": "Nominální hodnota",
      "type": "number"
    }
  },
  "definitions": {
    "instrumentIds": {
      "description": "Identifikátory CP",
      "type": "object",
      "required": [
        "ccpId",
        "ebrokerId"
      ],
      "properties": {
        "ccpId": {
          "type": "integer",
          "description": "Identifikace CP v CCP."
        },
        "ebrokerId": {
          "type": "integer",
          "description": "Identifikace CP v eBroker"
        },
        "topasId": {
          "type": [
            "integer",
            "null"
          ],
          "description": "Identifikace CP v TOPAS"
        }
      }
    }
  }
}